qichang_webagent/__init__.py
qichang_webagent/_bundle/__init__.py
qichang_webagent/core/__init__.py
qichang_webagent/core/action_engine.py
qichang_webagent/core/action_template.py
qichang_webagent/core/agents.py
qichang_webagent/core/base_driver.py
qichang_webagent/core/base_engine.py
qichang_webagent/core/context.py
qichang_webagent/core/display.py
qichang_webagent/core/evaluator.py
qichang_webagent/core/exceptions.py
qichang_webagent/core/extractors.py
qichang_webagent/core/listener.py
qichang_webagent/core/logger.py
qichang_webagent/core/memory.py
qichang_webagent/core/navigation.py
qichang_webagent/core/python_engine.py
qichang_webagent/core/retrievers.py
qichang_webagent/core/token_counter.py
qichang_webagent/core/world_model.py
qichang_webagent/gradio/__init__.py
qichang_webagent/gradio/base.py
qichang_webagent-0.1.4.dist-info/METADATA
qichang_webagent-0.1.4.dist-info/WHEEL
qichang_webagent-0.1.4.dist-info/top_level.txt
qichang_webagent-0.1.4.dist-info/RECORD
