Metadata-Version: 2.1
Name: qichang_webagent
Version: 0.1.4
Summary: This package is a improved version of LaVague
Author: Qichang Zheng
Author-email: qichang.zheng2000@gmail.com
Classifier: Programming Language :: Python :: 3
Classifier: License :: OSI Approved :: MIT License
Classifier: Operating System :: OS Independent
Requires-Python: >=3.10
